{
 "charts": [],
 "content": "[{\"id\":\"KXy0TP8iYw\",\"type\":\"custom_block\",\"data\":{\"custom_block_name\":\"Polmark Logo\",\"col\":12}},{\"id\":\"SUiWQV6kSY\",\"type\":\"custom_block\",\"data\":{\"custom_block_name\":\"Daftar Peta Zona Pemenangan\",\"col\":4}},{\"id\":\"7NgoePal0K\",\"type\":\"custom_block\",\"data\":{\"custom_block_name\":\"Daftar Wilayah Pendampingan\",\"col\":4}},{\"id\":\"hUKnJJ3gQT\",\"type\":\"custom_block\",\"data\":{\"custom_block_name\":\"widget module daftar dpt pilkada 2024\",\"col\":4}}]",
 "creation": "2024-10-22 13:14:36.560659",
 "custom_blocks": [
  {
   "custom_block_name": "widget logo polmark",
   "label": "Polmark Logo"
  },
  {
   "custom_block_name": "widget module daftar dpt pilkada 2024",
   "label": "widget module daftar dpt pilkada 2024"
  },
  {
   "custom_block_name": "widget module daftar peta zona pemenangan",
   "label": "Daftar Peta Zona Pemenangan"
  },
  {
   "custom_block_name": "widget module daftar wilayah pendampingan",
   "label": "Daftar Wilayah Pendampingan"
  }
 ],
 "docstatus": 0,
 "doctype": "Workspace",
 "for_user": "",
 "hide_custom": 0,
 "icon": "website",
 "idx": 0,
 "indicator_color": "green",
 "is_hidden": 0,
 "label": "Pendampingan",
 "links": [],
 "modified": "2024-10-22 16:06:51.194170",
 "modified_by": "Administrator",
 "module": "Polmark Dashboard",
 "name": "Pendampingan",
 "number_cards": [],
 "owner": "Administrator",
 "parent_page": "Polmark Indonesia",
 "public": 1,
 "quick_lists": [],
 "roles": [],
 "sequence_id": 3.0,
 "shortcuts": [],
 "title": "Pendampingan"
}